

{
  "itemIdentifier": "cdif.bbr.metadata.adaProperties.detailLAF",
  "$schema": "metaschema.yaml",
  "name": "LAF Instrument Detail",
  "abstract": "Laser Ablation Fluorescence processed/raw data detail properties. Defines properties: @type, elementAnalyzed, sampleMassConsumed, sampleType.",
  "status": "under-development",
  "dateTimeAddition": "2026-02-06T00:00:00Z",
  "itemClass": "schema",
  "register": "cdif-building-block-register",
  "version": "0.1",
  "dateOfLastChange": "2026-03-04",
  "link": "https://github.com/usgin/metadataBuildingBlocks",
  "maturity": "draft",
  "scope": "unstable",
  "tags": [
    "ada",
    "astromat",
    "instrument",
    "laf"
  ],
  "sources": [
    {
      "title": "ADA Metadata Schema v3",
      "link": "https://github.com/amds-ldeo/metadata"
    }
  ],
  "shaclShapes": {},
  "ldContext": "https://usgin.github.io/metadataBuildingBlocks/build/annotated/bbr/metadata/adaProperties/detailLAF/context.jsonld",
  "schema": {
    "application/yaml": "https://usgin.github.io/metadataBuildingBlocks/build/annotated/bbr/metadata/adaProperties/detailLAF/schema.yaml",
    "application/json": "https://usgin.github.io/metadataBuildingBlocks/build/annotated/bbr/metadata/adaProperties/detailLAF/schema.json"
  },
  "sourceSchema": "https://usgin.github.io/metadataBuildingBlocks/_sources/adaProperties/detailLAF/schema.yaml",
  "sourceLdContext": "https://usgin.github.io/metadataBuildingBlocks/_sources/adaProperties/detailLAF/context.jsonld",
  "sourceFiles": "https://usgin.github.io/metadataBuildingBlocks/_sources/adaProperties/detailLAF/",
  "rdfData": [],
  "validationPassed": true,
  "description": "# LAF Instrument Detail\n\nLaser Ablation Fluorescence processed/raw data. elementAnalyzed goes in resultTarget.\n",
  "annotatedSchema": "$schema: https://json-schema.org/draft/2020-12/schema\ntitle: LAF Instrument Detail\ndescription: Laser Ablation Fluorescence processed/raw data. elementAnalyzed goes\n  in resultTarget.\ntype: object\nproperties:\n  '@type':\n    anyOf:\n    - const: ada:LAFProcessed\n    - const: ada:LAFRaw\n  elementAnalyzed:\n    type: string\n  sampleMassConsumed:\n    type: string\n  sampleType:\n    type: string\nx-jsonld-prefixes:\n  schema: http://schema.org/\n  ada: https://ada.astromat.org/metadata/\n",
  "gitRepository": "https://github.com/usgin/metadataBuildingBlocks",
  "gitPath": "_sources/adaProperties/detailLAF"
}