{
  "$schema": "metaschema.yaml",
  "name": "ECRR Dataset profile",
  "abstract": "Complete ECRR metadata profile for dataset resources, composing base, common, assessment, and dataset-specific building blocks.",
  "status": "under-development",
  "dateTimeAddition": "2026-02-28T00:00:00Z",
  "itemClass": "schema",
  "register": "ecrr-building-block-register",
  "version": "0.1",
  "dateOfLastChange": "2026-02-28",
  "sources": [
    {
      "title": "EarthCube Resource Registry",
      "link": "https://www.earthcube.org/resource-registry"
    },
    {
      "title": "schema.org Dataset",
      "link": "https://schema.org/Dataset"
    }
  ],
  "maturity": "draft",
  "scope": "unstable",
  "tags": ["ecrr", "templates"]
}
